client/__init__.py
client/client.py
client/client_database.py
client/client_setup.py
client/database.py
client/decorators.py
client/descriptors.py
client/metaclasses.py
client/unit_tests/__init__.py
client/unit_tests/client.py
client/unit_tests/test_client.py
client/unit_tests/test_server.py
client/unit_tests/test_utils.py
server/__init__.py
server/database.py
server/decorators.py
server/descriptors.py
server/metaclasses.py
server/server.py
server/unit_tests/__init__.py
server/unit_tests/client.py
server/unit_tests/test_client.py
server/unit_tests/test_server.py
server/unit_tests/test_utils.py
messanger_client_my_ultra_unique_name-0.0.2.dist-info/METADATA
messanger_client_my_ultra_unique_name-0.0.2.dist-info/WHEEL
messanger_client_my_ultra_unique_name-0.0.2.dist-info/top_level.txt
messanger_client_my_ultra_unique_name-0.0.2.dist-info/RECORD
