Metadata-Version: 2.1
Name: messanger-client-my-ultra-unique-name
Version: 0.0.2
Summary: client_side_of_messanger
Author: Maxim
Author-email: 
Requires-Dist: PyQt5
Requires-Dist: tabulate
Requires-Dist: sqlalchemy
Requires-Dist: sphinx
Requires-Dist: wheel
Requires-Dist: cx-Freeze
